easy_technical_analysis/__init__.py
easy_technical_analysis/indicators.py
easy_technical_analysis/kite_login.py
easy_technical_analysis-0.0.2.dist-info/METADATA
easy_technical_analysis-0.0.2.dist-info/WHEEL
easy_technical_analysis-0.0.2.dist-info/RECORD
